projeto_pypi/__init__.py
projeto_pypi/funcoes.py
projeto_pypi-0.0.1.dist-info/licenses/License.txt
projeto_pypi-0.0.1.dist-info/METADATA
projeto_pypi-0.0.1.dist-info/WHEEL
projeto_pypi-0.0.1.dist-info/top_level.txt
projeto_pypi-0.0.1.dist-info/RECORD
