Metadata-Version: 2.4
Name: projeto-pypi
Version: 0.0.1
Summary: Um pacote simples para testes no PyPI
Home-page: https://github.com/LeonardoCigarra/projeto_pypi
Author: Seu Nome
Author-email: seuemail@example.com
Classifier: Programming Language :: Python :: 3
Classifier: License :: OSI Approved :: MIT License
Classifier: Operating System :: OS Independent
Requires-Python: >=3.6
License-File: License.txt
Dynamic: author
Dynamic: author-email
Dynamic: classifier
Dynamic: description
Dynamic: description-content-type
Dynamic: home-page
Dynamic: license-file
Dynamic: requires-python
Dynamic: summary
